article_search.py
mevzuat_client.py
mevzuat_mcp_server.py
mevzuat_models.py
mevzuat_mcp-0.3.0.dist-info/licenses/LICENSE
mevzuat_mcp-0.3.0.dist-info/METADATA
mevzuat_mcp-0.3.0.dist-info/WHEEL
mevzuat_mcp-0.3.0.dist-info/entry_points.txt
mevzuat_mcp-0.3.0.dist-info/top_level.txt
mevzuat_mcp-0.3.0.dist-info/RECORD
