Metadata-Version: 2.4
Name: mevzuat-mcp
Version: 0.3.0
Summary: MCP Server for Turkish Legislation - 18 tools for comprehensive access to Turkish laws, decrees, regulations and circulars
Author-email: Said Surucu <saidsrc@gmail.com>
License: MIT
Project-URL: Homepage, https://github.com/saidsurucu/mevzuat-mcp
Project-URL: Bug Tracker, https://github.com/saidsurucu/mevzuat-mcp/issues
Project-URL: Repository, https://github.com/saidsurucu/mevzuat-mcp
Keywords: mcp,mevzuat,turkish-law,legislation,claude,llm,kanun,khk,tuzuk,yonetmelik
Classifier: Development Status :: 4 - Beta
Classifier: Intended Audience :: Developers
Classifier: License :: OSI Approved :: MIT License
Classifier: Programming Language :: Python :: 3
Classifier: Programming Language :: Python :: 3.11
Classifier: Programming Language :: Python :: 3.12
Classifier: Topic :: Software Development :: Libraries :: Python Modules
Classifier: Topic :: Text Processing :: Markup :: Markdown
Requires-Python: >=3.11
License-File: LICENSE
Requires-Dist: fastmcp>=2.12.0
Requires-Dist: pydantic>=2.0.0
Requires-Dist: httpx>=0.24.0
Requires-Dist: beautifulsoup4>=4.12.0
Requires-Dist: lxml>=4.9.0
Requires-Dist: markitdown[pdf]==0.1.3
Requires-Dist: playwright==1.55.0
Requires-Dist: mistralai>=1.0.0
Requires-Dist: python-dotenv>=1.0.0
Requires-Dist: fastapi>=0.100.0
Requires-Dist: uvicorn>=0.23.0
Dynamic: license-file
